MANIFEST.in
README.md
requirements.txt
setup.py
baiji/__init__.py
baiji/pod/__init__.py
baiji/pod/asset_cache.py
baiji/pod/asset_pack.py
baiji/pod/config.py
baiji/pod/package_version.py
baiji/pod/prefill.py
baiji/pod/test_asset_cache.py
baiji/pod/runners/__init__.py
baiji/pod/runners/asset_pack_runner.py
baiji/pod/runners/cache_util_runner.py
baiji/pod/runners/prefill_runner.py
baiji/pod/runners/test_cache_util_runner.py
baiji/pod/runners/vc_runner.py
baiji/pod/util/__init__.py
baiji/pod/util/format_bytes.py
baiji/pod/util/json.py
baiji/pod/util/reachability.py
baiji/pod/util/shutillib.py
baiji/pod/util/yaml.py
baiji/pod/versioned/__init__.py
baiji/pod/versioned/core.py
baiji/pod/versioned/test_core.py
baiji/pod/versioned/uploader.py
bin/baiji-cache
bin/baiji-pack
bin/baiji-prefill
bin/vc
metabaiji_pod.egg-info/PKG-INFO
metabaiji_pod.egg-info/SOURCES.txt
metabaiji_pod.egg-info/dependency_links.txt
metabaiji_pod.egg-info/requires.txt
metabaiji_pod.egg-info/top_level.txt