Metadata-Version: 1.1
Name: metabaiji-pod
Version: 1.1.1
Summary: Active fork of baiji-pod, Body Labs' asset cache for S3 using baiji
Home-page: https://github.com/metabolize/baiji-pod
Author: Body Labs
Author-email: alex@bodylabs.com, paul.melnikow@bodylabs.com
License: Apache
Platform: UNKNOWN
Classifier: Development Status :: 3 - Alpha
Classifier: Intended Audience :: Developers
Classifier: License :: OSI Approved :: MIT License
Classifier: Operating System :: OS Independent
Classifier: Programming Language :: Python :: 2.7
Classifier: Programming Language :: Python :: 3
